iamauth/__init__.py
iamauth/__main__.py
iamauth/sigv4.py
iamauth/sigv4a.py
iamauth-0.7.0.dist-info/entry_points.txt
iamauth-0.7.0.dist-info/LICENSE
iamauth-0.7.0.dist-info/WHEEL
iamauth-0.7.0.dist-info/METADATA
iamauth-0.7.0.dist-info/RECORD
