Metadata-Version: 2.1
Name: iamauth
Version: 0.7.0
Summary: AWS IAM Authorizer.
Author-email: Alexander Mancevice <alexander.mancevice@hey.com>
Requires-Python: >= 3.7
Classifier: Development Status :: 5 - Production/Stable
Classifier: Environment :: Console
Classifier: Intended Audience :: Developers
Classifier: License :: OSI Approved :: MIT License
Classifier: Operating System :: OS Independent
Classifier: Programming Language :: Python :: 3
Classifier: Programming Language :: Python :: 3.7
Classifier: Programming Language :: Python :: 3.8
Classifier: Programming Language :: Python :: 3.9
Classifier: Programming Language :: Python :: 3.10
Classifier: Programming Language :: Python :: 3.11
Classifier: Topic :: Utilities
Requires-Dist: awscrt
Requires-Dist: boto3
Requires-Dist: requests
Project-URL: Home, https://github.com/amancevice/requests-iamauth
